sushi_allergy_parser/__init__.py
sushi_allergy_parser/base.py
sushi_allergy_parser/kura.py
sushi_allergy_parser/sushiro.py
sushi_allergy_parser/util.py
sushi_allergy_parser-0.1.3.dist-info/LICENSE
sushi_allergy_parser-0.1.3.dist-info/WHEEL
sushi_allergy_parser-0.1.3.dist-info/METADATA
sushi_allergy_parser-0.1.3.dist-info/RECORD
