Metadata-Version: 2.1
Name: sushi-allergy-parser
Version: 0.1.3
Summary: sushi-allergy-parser is a parser for allergy infomation document of japanese conveyor-belt sushi chain. 
Home-page: https://github.com/t3yamoto/sushi-allergy-parser
License: MIT
Author: t3yamoto
Author-email: 3yamoto.dev@gmail.com
Requires-Python: >=3.7,<4.0
Classifier: Development Status :: 3 - Alpha
Classifier: Environment :: Console
Classifier: License :: OSI Approved :: MIT License
Classifier: Programming Language :: Python :: 3
Classifier: Programming Language :: Python :: 3.7
Classifier: Topic :: Utilities
Requires-Dist: tabula-py (>=1.4,<2.0)
Project-URL: Repository, https://github.com/t3yamoto/sushi-allergy-parser
